whathammers/__init__.py
whathammers/reports.py
whathammers/utils.py
whathammers/whathammers.py
whathammers-0.1.0.dist-info/DESCRIPTION.rst
whathammers-0.1.0.dist-info/METADATA
whathammers-0.1.0.dist-info/RECORD
whathammers-0.1.0.dist-info/WHEEL
whathammers-0.1.0.dist-info/entry_points.txt
whathammers-0.1.0.dist-info/metadata.json
whathammers-0.1.0.dist-info/top_level.txt
