Metadata-Version: 2.0
Name: whathammers
Version: 0.1.0
Summary: Command line tool for quick analysis of Apache log files
Home-page: https://gitlab.com/aliceh75/whathammers
Author: Alice Heaton
Author-email: UNKNOWN
License: GPLv3+
Keywords: apache logfile analysis
Platform: UNKNOWN
Classifier: Development Status :: 4 - Beta
Classifier: Environment :: Console
Classifier: Intended Audience :: System Administrators
Classifier: License :: OSI Approved :: GNU General Public License v3 or later (GPLv3+)
Classifier: Operating System :: OS Independent
Classifier: Programming Language :: Python
Classifier: Programming Language :: Python :: 2
Classifier: Programming Language :: Python :: 2.7
Requires-Dist: apache-log-parser
